{
  "openapi": "3.0.1",
  "info": {
    "title": "HQ.Backend",
    "version": "1.0"
  },
  "paths": {
    "/api/Auth/register": {
      "post": {
        "tags": [
          "Auth"
        ],
        "requestBody": {
          "content": {
            "application/json": {
              "schema": {
                "$ref": "#/components/schemas/User"
              }
            },
            "text/json": {
              "schema": {
                "$ref": "#/components/schemas/User"
              }
            },
            "application/*+json": {
              "schema": {
                "$ref": "#/components/schemas/User"
              }
            }
          }
        },
        "responses": {
          "200": {
            "description": "OK"
          }
        }
      }
    },
    "/api/Auth/login": {
      "post": {
        "tags": [
          "Auth"
        ],
        "requestBody": {
          "content": {
            "application/json": {
              "schema": {
                "$ref": "#/components/schemas/LoginRequest"
              }
            },
            "text/json": {
              "schema": {
                "$ref": "#/components/schemas/LoginRequest"
              }
            },
            "application/*+json": {
              "schema": {
                "$ref": "#/components/schemas/LoginRequest"
              }
            }
          }
        },
        "responses": {
          "200": {
            "description": "OK"
          }
        }
      }
    },
    "/api/Auth/google-login": {
      "post": {
        "tags": [
          "Auth"
        ],
        "requestBody": {
          "content": {
            "application/json": {
              "schema": {
                "$ref": "#/components/schemas/GoogleLoginRequest"
              }
            },
            "text/json": {
              "schema": {
                "$ref": "#/components/schemas/GoogleLoginRequest"
              }
            },
            "application/*+json": {
              "schema": {
                "$ref": "#/components/schemas/GoogleLoginRequest"
              }
            }
          }
        },
        "responses": {
          "200": {
            "description": "OK"
          }
        }
      }
    },
    "/api/Cart/add": {
      "post": {
        "tags": [
          "Cart"
        ],
        "requestBody": {
          "content": {
            "application/json": {
              "schema": {
                "$ref": "#/components/schemas/AddToCartRequest"
              }
            },
            "text/json": {
              "schema": {
                "$ref": "#/components/schemas/AddToCartRequest"
              }
            },
            "application/*+json": {
              "schema": {
                "$ref": "#/components/schemas/AddToCartRequest"
              }
            }
          }
        },
        "responses": {
          "200": {
            "description": "OK"
          }
        }
      }
    },
    "/api/Cart/{userId}": {
      "get": {
        "tags": [
          "Cart"
        ],
        "parameters": [
          {
            "name": "userId",
            "in": "path",
            "required": true,
            "schema": {
              "type": "integer",
              "format": "int32"
            }
          }
        ],
        "responses": {
          "200": {
            "description": "OK"
          }
        }
      }
    },
    "/api/Cart/remove/{cartItemId}": {
      "delete": {
        "tags": [
          "Cart"
        ],
        "parameters": [
          {
            "name": "cartItemId",
            "in": "path",
            "required": true,
            "schema": {
              "type": "integer",
              "format": "int32"
            }
          }
        ],
        "responses": {
          "200": {
            "description": "OK"
          }
        }
      }
    },
    "/api/News": {
      "get": {
        "tags": [
          "News"
        ],
        "responses": {
          "200": {
            "description": "OK"
          }
        }
      }
    },
    "/api/News/categories": {
      "get": {
        "tags": [
          "News"
        ],
        "responses": {
          "200": {
            "description": "OK"
          }
        }
      }
    },
    "/api/News/titles": {
      "get": {
        "tags": [
          "News"
        ],
        "responses": {
          "200": {
            "description": "OK"
          }
        }
      }
    },
    "/api/News/{id}": {
      "get": {
        "tags": [
          "News"
        ],
        "parameters": [
          {
            "name": "id",
            "in": "path",
            "required": true,
            "schema": {
              "type": "integer",
              "format": "int32"
            }
          }
        ],
        "responses": {
          "200": {
            "description": "OK"
          }
        }
      }
    },
    "/api/Products": {
      "get": {
        "tags": [
          "Products"
        ],
        "responses": {
          "200": {
            "description": "OK"
          }
        }
      }
    },
    "/api/Products/categories": {
      "get": {
        "tags": [
          "Products"
        ],
        "responses": {
          "200": {
            "description": "OK"
          }
        }
      }
    },
    "/api/Products/{id}": {
      "get": {
        "tags": [
          "Products"
        ],
        "parameters": [
          {
            "name": "id",
            "in": "path",
            "required": true,
            "schema": {
              "type": "integer",
              "format": "int32"
            }
          }
        ],
        "responses": {
          "200": {
            "description": "OK"
          }
        }
      }
    },
    "/api/Promotions": {
      "get": {
        "tags": [
          "Promotions"
        ],
        "responses": {
          "200": {
            "description": "OK"
          }
        }
      }
    },
    "/api/Services": {
      "get": {
        "tags": [
          "Services"
        ],
        "responses": {
          "200": {
            "description": "OK"
          }
        }
      }
    }
  },
  "components": {
    "schemas": {
      "AddToCartRequest": {
        "type": "object",
        "properties": {
          "userId": {
            "type": "integer",
            "format": "int32"
          },
          "variantId": {
            "type": "integer",
            "format": "int32"
          },
          "quantity": {
            "type": "integer",
            "format": "int32"
          }
        },
        "additionalProperties": false
      },
      "GoogleLoginRequest": {
        "type": "object",
        "properties": {
          "token": {
            "type": "string",
            "nullable": true
          }
        },
        "additionalProperties": false
      },
      "LoginRequest": {
        "type": "object",
        "properties": {
          "email": {
            "type": "string",
            "nullable": true
          },
          "password": {
            "type": "string",
            "nullable": true
          }
        },
        "additionalProperties": false
      },
      "User": {
        "type": "object",
        "properties": {
          "id": {
            "type": "integer",
            "format": "int32"
          },
          "password": {
            "type": "string",
            "nullable": true
          },
          "email": {
            "type": "string",
            "nullable": true
          },
          "role": {
            "type": "string",
            "nullable": true
          },
          "authProvider": {
            "type": "string",
            "nullable": true
          },
          "googleId": {
            "type": "string",
            "nullable": true
          },
          "fullName": {
            "type": "string",
            "nullable": true
          },
          "phone": {
            "type": "string",
            "nullable": true
          },
          "address": {
            "type": "string",
            "nullable": true
          },
          "avatarUrl": {
            "type": "string",
            "nullable": true
          },
          "status": {
            "type": "boolean"
          },
          "createdAt": {
            "type": "string",
            "format": "date-time"
          }
        },
        "additionalProperties": false
      }
    }
  }
}